Metadata-Version: 2.1
Name: tts-scores
Version: 1.0.0
Summary: A library for computing performance metrics for text-to-speech systems
Home-page: https://github.com/neonbjb/tts-scores
Author: James
Author-email: james@adamant.ai
License: UNKNOWN
Download-URL: https://github.com/neonbjb/tts-scores/archive/refs/tags/1.0.0.tar.gz
Platform: UNKNOWN
Classifier: Programming Language :: Python :: 3
Classifier: License :: OSI Approved :: Apache Software License
Classifier: Operating System :: OS Independent
Requires-Python: >=3.6
